athena_cli.py
athena_cli-0.1.13.dist-info/LICENSE
athena_cli-0.1.13.dist-info/METADATA
athena_cli-0.1.13.dist-info/NOTICE
athena_cli-0.1.13.dist-info/WHEEL
athena_cli-0.1.13.dist-info/entry_points.txt
athena_cli-0.1.13.dist-info/top_level.txt
athena_cli-0.1.13.dist-info/zip-safe
athena_cli-0.1.13.dist-info/RECORD
