Metadata-Version: 2.1
Name: athena-cli
Version: 0.1.13
Summary: Presto-like CLI for AWS Athena
Home-page: https://github.com/satterly/athena-cli
Author: Nick Satterly
Author-email: nick.satterly@gmail.com
License: Apache License 2.0
Keywords: aws athena presto cli
Classifier: Topic :: Utilities
Requires-Python: >=3.5
License-File: LICENSE
License-File: NOTICE
Requires-Dist: boto3 (>=1.4.4)
Requires-Dist: cmd2 (>=0.9.0.1)
Requires-Dist: tabulate (>=0.8.1)
